xrframes/__init__.py
xrframes/_rich_dask.py
xrframes/_rich_joblib.py
xrframes/core.py
xrframes/py.typed
xrframes/util.py
xrframes-0.0.4.dist-info/LICENSE
xrframes-0.0.4.dist-info/WHEEL
xrframes-0.0.4.dist-info/METADATA
xrframes-0.0.4.dist-info/RECORD
