Metadata-Version: 2.1
Name: xrframes
Version: 0.0.4
Summary: Similar to ``xmovie``, make animations from xarray objects.
Author-email: zmoon <zmoon92@gmail.com>
Requires-Python: ~=3.9
Classifier: License :: OSI Approved :: MIT License
Requires-Dist: rich
Project-URL: Home, https://github.com/zmoon/xrframes
Project-URL: Source, https://github.com/zmoon/xrframes
